{
    "avatar": "images\/4\/691692849687959.jpg",
    "tagline": "You kill em' we grill",
    "social": {
        "facebook": "ggg",
        "twitter": "",
        "linkedin": "twiter ",
        "instagram": "",
        "youtube": ""
    },
    "links": {
        "24807a22-f81c-4c2e-abff-20fbbf0c6675": {
            "id": "24807a22-f81c-4c2e-abff-20fbbf0c6675",
            "type": "standard",
            "icon": "",
            "url": "fff",
            "clicks": 0
        },
        "ba3a21fb-42db-4873-9399-4b3725b36c16": {
            "id": "ba3a21fb-42db-4873-9399-4b3725b36c16",
            "type": "video",
            "icon": "",
            "url": "",
            "clicks": 0
        }
    },
    "linktree_id": "1"
}